t77_date/__init__.py
t77_date/constants.py
t77_date/datetime.py
t77_date/timedelta.py
t77_date-0.5.0.dist-info/DESCRIPTION.rst
t77_date-0.5.0.dist-info/METADATA
t77_date-0.5.0.dist-info/RECORD
t77_date-0.5.0.dist-info/WHEEL
t77_date-0.5.0.dist-info/metadata.json
t77_date-0.5.0.dist-info/top_level.txt
